decorators/__init__.py
indently_decorators-1.0.0.dist-info/licenses/LICENSE
indently_decorators-1.0.0.dist-info/METADATA
indently_decorators-1.0.0.dist-info/WHEEL
indently_decorators-1.0.0.dist-info/top_level.txt
indently_decorators-1.0.0.dist-info/RECORD
